MANIFEST.in
setup.cfg
setup.py
panoramix/__init__.py
panoramix/ascii_art.py
panoramix/config.py
panoramix/forms.py
panoramix/models.py
panoramix/utils.py
panoramix/views.py
panoramix/viz.py
panoramix.egg-info/PKG-INFO
panoramix.egg-info/SOURCES.txt
panoramix.egg-info/dependency_links.txt
panoramix.egg-info/not-zip-safe
panoramix.egg-info/requires.txt
panoramix.egg-info/top_level.txt
panoramix/bin/__init__.py
panoramix/bin/panoramix
panoramix/data/__init__.py
panoramix/data/__init__.pyc
panoramix/data/birth_names.csv.gz
panoramix/data/birth_names.json.gz
panoramix/data/countries.json.gz
panoramix/data/countries.md
panoramix/data/countries.py
panoramix/data/countries.pyc
panoramix/migrations/README
panoramix/migrations/__init__.py
panoramix/migrations/alembic.ini
panoramix/migrations/env.py
panoramix/migrations/env.pyc
panoramix/migrations/script.py.mako
panoramix/migrations/versions/12d55656cbca_is_featured.py
panoramix/migrations/versions/12d55656cbca_is_featured.pyc
panoramix/migrations/versions/1a48a5411020_adding_slug_to_dash.py
panoramix/migrations/versions/1a48a5411020_adding_slug_to_dash.pyc
panoramix/migrations/versions/1e2841a4128_.py
panoramix/migrations/versions/1e2841a4128_.pyc
panoramix/migrations/versions/2591d77e9831_user_id.py
panoramix/migrations/versions/2591d77e9831_user_id.pyc
panoramix/migrations/versions/289ce07647b_add_encrypted_password_field.py
panoramix/migrations/versions/289ce07647b_add_encrypted_password_field.pyc
panoramix/migrations/versions/2929af7925ed_tz_offsets_in_data_sources.py
panoramix/migrations/versions/2929af7925ed_tz_offsets_in_data_sources.pyc
panoramix/migrations/versions/315b3f4da9b0_adding_log_model.py
panoramix/migrations/versions/315b3f4da9b0_adding_log_model.pyc
panoramix/migrations/versions/430039611635_log_more.py
panoramix/migrations/versions/430039611635_log_more.pyc
panoramix/migrations/versions/43df8de3a5f4_dash_json.py
panoramix/migrations/versions/43df8de3a5f4_dash_json.pyc
panoramix/migrations/versions/4e6a06bad7a8_init.py
panoramix/migrations/versions/4e6a06bad7a8_init.pyc
panoramix/migrations/versions/55179c7f25c7_sqla_descr.py
panoramix/migrations/versions/55179c7f25c7_sqla_descr.pyc
