Metadata-Version: 1.1
Name: panoramix
Version: 0.8.0
Summary: A interactive data visualization platform build on SqlAlchemy and druid.io
Home-page: https://github.com/mistercrunch/panoramix
Author: Maxime Beauchemin
Author-email: maximebeauchemin@gmail.com
License: UNKNOWN
Download-URL: https://github.com/mistercrunch/panoramix/tarball/0.8.0
Platform: UNKNOWN
